jupyter_trame_proxy/__init__.py
jupyter_trame_proxy/icons/logo.svg
jupyter_trame_proxy/share/launch_trame.sh
jupyter_trame_proxy-0.2.0.dist-info/LICENSE
jupyter_trame_proxy-0.2.0.dist-info/METADATA
jupyter_trame_proxy-0.2.0.dist-info/WHEEL
jupyter_trame_proxy-0.2.0.dist-info/entry_points.txt
jupyter_trame_proxy-0.2.0.dist-info/top_level.txt
jupyter_trame_proxy-0.2.0.dist-info/RECORD
