Metadata-Version: 2.1
Name: jupyter-trame-proxy
Version: 0.2.0
Summary: ParaView trame proxy for JupyterLab
Home-page: https://github.com/jwindgassen/jupyter-trame-proxy
Download-URL: https://github.com/jwindgassen/jupyter-trame-proxy/archive/v0.2.0.tar.gz
Author: Jonathan Windgassen
Author-email: j.windgassen@fz-juelich.de
Keywords: jupyter,trame,paraview,jupyterhub,jupyter-server-proxy
Classifier: Programming Language :: Python :: 3
Classifier: License :: OSI Approved :: BSD License
Classifier: Operating System :: OS Independent
Classifier: Framework :: Jupyter
Requires-Python: >=3.9
License-File: LICENSE
Requires-Dist: jupyter-server-proxy (>=3.1.0)
